LICENSE
openap/polymer/__init__.py
openap/polymer/data/a19n.csv
openap/polymer/data/a20n.csv
openap/polymer/data/a21n.csv
openap/polymer/data/a319.csv
openap/polymer/data/a320.csv
openap/polymer/data/a321.csv
openap/polymer/data/a332.csv
openap/polymer/data/a333.csv
openap/polymer/data/a343.csv
openap/polymer/data/a359.csv
openap/polymer/data/a388.csv
openap/polymer/data/b37m.csv
openap/polymer/data/b38m.csv
openap/polymer/data/b39m.csv
openap/polymer/data/b3xm.csv
openap/polymer/data/b734.csv
openap/polymer/data/b737.csv
openap/polymer/data/b738.csv
openap/polymer/data/b739.csv
openap/polymer/data/b744.csv
openap/polymer/data/b748.csv
openap/polymer/data/b752.csv
openap/polymer/data/b763.csv
openap/polymer/data/b772.csv
openap/polymer/data/b773.csv
openap/polymer/data/b77w.csv
openap/polymer/data/b788.csv
openap/polymer/data/b789.csv
openap/polymer/data/c550.csv
openap/polymer/data/e145.csv
openap/polymer/data/e170.csv
openap/polymer/data/e190.csv
openap/polymer/data/e195.csv
openap/polymer/data/e75l.csv
openap/polymer/data/glf6.csv
openap/polymer/script/construct.py
openap_polymer-0.1.dist-info/LICENSE
openap_polymer-0.1.dist-info/METADATA
openap_polymer-0.1.dist-info/WHEEL
openap_polymer-0.1.dist-info/RECORD
