Metadata-Version: 2.1
Name: openap-polymer
Version: 0.1
Summary: OpenAP Polynomial Model for Emission Research
License: GNU Lesser General Public License v3 (LGPLv3)
Author: Junzi Sun
Author-email: j.sun-1@tudelft.nl
Requires-Python: >=3.7
Classifier: Development Status :: 3 - Alpha
Classifier: Intended Audience :: Developers
Classifier: License :: OSI Approved :: GNU Lesser General Public License v3 (LGPLv3)
Classifier: License :: Other/Proprietary License
Classifier: Programming Language :: Python :: 3
Classifier: Programming Language :: Python :: 3.7
Classifier: Programming Language :: Python :: 3.8
Classifier: Programming Language :: Python :: 3.9
Classifier: Programming Language :: Python :: 3.10
Classifier: Programming Language :: Python :: 3.11
Classifier: Topic :: Software Development :: Libraries :: Python Modules
Requires-Dist: openap (>=1.3)
